_soundfile.py
soundfile.py
_soundfile_data/COPYING
_soundfile_data/__init__.py
_soundfile_data/libsndfile_x86_64.so
soundfile-0.13.1.dist-info/LICENSE
soundfile-0.13.1.dist-info/METADATA
soundfile-0.13.1.dist-info/WHEEL
soundfile-0.13.1.dist-info/top_level.txt
soundfile-0.13.1.dist-info/RECORD
